flash_flood-0.4.3.data/scripts/authorize_aws_deploy.sh
flashflood/__init__.py
flashflood/config.py
flashflood/exceptions.py
flashflood/identifiers.py
flashflood/key_index.py
flashflood/objects.py
flashflood/util.py
flashflood/version.py
tests/infra/__init__.py
flash_flood-0.4.3.dist-info/LICENSE
flash_flood-0.4.3.dist-info/METADATA
flash_flood-0.4.3.dist-info/WHEEL
flash_flood-0.4.3.dist-info/top_level.txt
flash_flood-0.4.3.dist-info/RECORD
