Metadata-Version: 2.1
Name: flash-flood
Version: 0.4.3
Summary: Event journaling providing distributed playback.
Home-page: https://github.com/xbrianh/flash-flood.git/
Author: Brian Hannafious
Author-email: bhannafi@ucsc.edu
License: MIT
Platform: MacOS X
Platform: Posix
Classifier: Intended Audience :: Developers
Classifier: License :: OSI Approved :: MIT License
Classifier: Operating System :: MacOS :: MacOS X
Classifier: Operating System :: POSIX
Classifier: Programming Language :: Python :: 3.6
Requires-Dist: boto3 (>=1.7.13)
Requires-Dist: requests (>=2.20.0)
